settings/__init__.py
settings/management/__init__.py
settings/management/commands/__init__.py
settings/management/commands/createcomponent.py
cmponentsDjangoType-0.0.1.dist-info/LICENSE
cmponentsDjangoType-0.0.1.dist-info/METADATA
cmponentsDjangoType-0.0.1.dist-info/WHEEL
cmponentsDjangoType-0.0.1.dist-info/top_level.txt
cmponentsDjangoType-0.0.1.dist-info/RECORD
